.gitignore
LICENSE
README.md
setup.py
test.py
commandmap/__init__.py
commandmap.egg-info/PKG-INFO
commandmap.egg-info/SOURCES.txt
commandmap.egg-info/dependency_links.txt
commandmap.egg-info/top_level.txt