Metadata-Version: 2.1
Name: commandmap
Version: 1.0.0
Summary: A small module for mapping commands onto object methods by prefix.
Home-page: https://github.com/lainproliant/commandmap
Author: Lain Musgrove (lainproliant)
Author-email: lainproliant@gmail.com
License: BSD
Keywords: mapping commands cli
Classifier: Development Status :: 5 - Production/Stable
Classifier: Intended Audience :: Developers
Classifier: Topic :: Software Development :: Libraries :: Application Frameworks
Classifier: License :: OSI Approved :: BSD License
Classifier: Programming Language :: Python :: 3.10
Classifier: Programming Language :: Python :: 3.11
License-File: LICENSE
